<?xml version="1.0" encoding="utf-8" ?>
<dwsync>
<file name="ar.js" server="Z:/" local="131353721608724070" remote="131353721600000000" Dst="0" />
<file name="bg.js" server="Z:/" local="131353721608751401" remote="131353721600000000" Dst="0" />
<file name="ca.js" server="Z:/" local="131353721608771437" remote="131353721600000000" Dst="0" />
<file name="cs.js" server="Z:/" local="131353721608791451" remote="131353721600000000" Dst="0" />
<file name="cy.js" server="Z:/" local="131353721608811461" remote="131353721600000000" Dst="0" />
<file name="de.js" server="Z:/" local="131353721608831471" remote="131353721600000000" Dst="0" />
<file name="el.js" server="Z:/" local="131353721608851494" remote="131353721600000000" Dst="0" />
<file name="en-gb.js" server="Z:/" local="131353721608901534" remote="131353721600000000" Dst="0" />
<file name="en.js" server="Z:/" local="131353721608921543" remote="131353721600000000" Dst="0" />
<file name="eo.js" server="Z:/" local="131353721608941558" remote="131353721600000000" Dst="0" />
<file name="es.js" server="Z:/" local="131353721608961580" remote="131353721600000000" Dst="0" />
<file name="et.js" server="Z:/" local="131353721608971575" remote="131353721600000000" Dst="0" />
<file name="fa.js" server="Z:/" local="131353721608991589" remote="131353721600000000" Dst="0" />
<file name="fi.js" server="Z:/" local="131353721609001600" remote="131353721600000000" Dst="0" />
<file name="fr-ca.js" server="Z:/" local="131353721609061797" remote="131353721600000000" Dst="0" />
<file name="fr.js" server="Z:/" local="131353721609080597" remote="131353721600000000" Dst="0" />
<file name="gl.js" server="Z:/" local="131353721609090625" remote="131353721600000000" Dst="0" />
<file name="he.js" server="Z:/" local="131353721609110635" remote="131353721600000000" Dst="0" />
<file name="hr.js" server="Z:/" local="131353721609130649" remote="131353721600000000" Dst="0" />
<file name="hu.js" server="Z:/" local="131353721609150668" remote="131353721600000000" Dst="0" />
<file name="id.js" server="Z:/" local="131353721609170686" remote="131353721600000000" Dst="0" />
<file name="it.js" server="Z:/" local="131353721609231687" remote="131353721600000000" Dst="0" />
<file name="ja.js" server="Z:/" local="131353721609241728" remote="131353721600000000" Dst="0" />
<file name="km.js" server="Z:/" local="131353721609261734" remote="131353721600000000" Dst="0" />
<file name="ku.js" server="Z:/" local="131353721609281748" remote="131353721600000000" Dst="0" />
<file name="lv.js" server="Z:/" local="131353721609301758" remote="131353721600000000" Dst="0" />
<file name="nb.js" server="Z:/" local="131353721609317462" remote="131353721600000000" Dst="0" />
<file name="nl.js" server="Z:/" local="131353721609327486" remote="131353721600000000" Dst="0" />
<file name="no.js" server="Z:/" local="131353721609367630" remote="131353721600000000" Dst="0" />
<file name="pl.js" server="Z:/" local="131353721609407547" remote="131353721600000000" Dst="0" />
<file name="pt-br.js" server="Z:/" local="131353721609417554" remote="131353721600000000" Dst="0" />
<file name="pt.js" server="Z:/" local="131353721609437568" remote="131353721600000000" Dst="0" />
<file name="ru.js" server="Z:/" local="131353721609457621" remote="131353721600000000" Dst="0" />
<file name="si.js" server="Z:/" local="131353721609475493" remote="131353721600000000" Dst="0" />
<file name="sk.js" server="Z:/" local="131353721609485517" remote="131353721600000000" Dst="0" />
<file name="sl.js" server="Z:/" local="131353721609505527" remote="131353721600000000" Dst="0" />
<file name="sq.js" server="Z:/" local="131353721609545560" remote="131353721600000000" Dst="0" />
<file name="sv.js" server="Z:/" local="131353721609576342" remote="131353721600000000" Dst="0" />
<file name="th.js" server="Z:/" local="131353721609594492" remote="131353721600000000" Dst="0" />
<file name="tr.js" server="Z:/" local="131353721609604520" remote="131353721600000000" Dst="0" />
<file name="tt.js" server="Z:/" local="131353721609625420" remote="131353721600000000" Dst="0" />
<file name="ug.js" server="Z:/" local="131353721609635448" remote="131353721600000000" Dst="0" />
<file name="uk.js" server="Z:/" local="131353721609655458" remote="131353721600000000" Dst="0" />
<file name="vi.js" server="Z:/" local="131353721609675481" remote="131353721600000000" Dst="0" />
<file name="zh-cn.js" server="Z:/" local="131353721609715514" remote="131353721600000000" Dst="0" />
<file name="zh.js" server="Z:/" local="131353721609735519" remote="131353721600000000" Dst="0" />
<file name="_translationstatus.txt" server="Z:/" local="131353721609760939" remote="131353721600000000" Dst="0" />
</dwsync>