<?xml version="1.0" encoding="utf-8" ?>
<dwsync>
<file name="agenda-views.html" server="Z:/" local="131199671951335345" remote="131199671950000000" Dst="0" />
<file name="background-events.html" server="Z:/" local="131199671951355180" remote="131199671950000000" Dst="0" />
<file name="basic-views.html" server="Z:/" local="131199671951365183" remote="131199671950000000" Dst="0" />
<file name="default.html" server="Z:/" local="131199671951375186" remote="131199671950000000" Dst="0" />
<file name="external-dragging.html" server="Z:/" local="131199671951375186" remote="131199671950000000" Dst="0" />
<file name="gcal.html" server="Z:/" local="131199671951545311" remote="131199671950000000" Dst="0" />
<file name="json.html" server="Z:/" local="131199671951565325" remote="131199671950000000" Dst="0" />
<file name="languages.html" server="Z:/" local="131199671951615545" remote="131199671950000000" Dst="0" />
<file name="selectable.html" server="Z:/" local="131199671951970844" remote="131199671950000000" Dst="0" />
<file name="theme.html" server="Z:/" local="131199671952186015" remote="131199671950000000" Dst="0" />
<file name="timezones.html" server="Z:/" local="131199671952405992" remote="131199671950000000" Dst="0" />
</dwsync>