<?xml version="1.0" encoding="utf-8" ?>
<dwsync>
<file name="bg_siscar1.png" server="Z:/" local="131396940468225272" remote="131396940460000000" Dst="0" />
<file name="bg_siscar2.png" server="Z:/" local="131396940905881473" remote="131396940900000000" Dst="0" />
<file name="bg_siscar3.png" server="Z:/" local="131396941314686580" remote="131396941310000000" Dst="0" />
<file name="frontier1.png" server="Z:/" local="131370968974382918" remote="131370968970000000" Dst="0" />
<file name="frontier2.png" server="Z:/" local="131370969205414225" remote="131370969200000000" Dst="0" />
<file name="nissan.jpg" server="Z:/" local="131363988006157764" remote="131363988000000000" Dst="0" />
<file name="ico-siscar.jpg" server="Z:/" local="131442083215760830" remote="131442083210000000" Dst="0" />
<file name="DSC_5870.JPG" server="Z:/" local="131424457310000000" remote="131424457310000000" Dst="0" />
</dwsync>